COPYING.txt
DOCUMENTATION.html
INSTALL.txt
setup.cfg
setup.py
openopt/__init__.py
openopt/oo.py
openopt/ooVersionNumber.py
openopt.egg-info/PKG-INFO
openopt.egg-info/SOURCES.txt
openopt.egg-info/dependency_links.txt
openopt.egg-info/not-zip-safe
openopt.egg-info/requires.txt
openopt.egg-info/top_level.txt
openopt/doc/DOCUMENTATION.html
openopt/doc/badlyScaled.py
openopt/doc/checkDerivatives.py
openopt/doc/lpToMPS.py
openopt/doc/milpToMPS.py
openopt/doc/oosolver.py
openopt/doc/probAssign.py
openopt/doc/restricted_dom.py
openopt/doc/solverParams.py
openopt/doc/textOutput.py
openopt/doc/userArgs.py
openopt/doc/userCallback.py
openopt/examples/GUI_1.py
openopt/examples/__init__.py
openopt/examples/bpp_1.py
openopt/examples/bpp_2.py
openopt/examples/dfp_1.py
openopt/examples/dfp_2.py
openopt/examples/dsp_1.py
openopt/examples/eig_1.py
openopt/examples/eig_2.py
openopt/examples/glp_1.py
openopt/examples/glp_2.py
openopt/examples/glp_3.py
openopt/examples/glp_Ab_c.py
openopt/examples/ksp_1.py
openopt/examples/ksp_2.py
openopt/examples/ksp_mop.py
openopt/examples/lcp_1.py
openopt/examples/llavp_1.py
openopt/examples/llsp_1.py
openopt/examples/llsp_2.py
openopt/examples/lp_1.py
openopt/examples/lunp_1.py
openopt/examples/mcp_1.py
openopt/examples/milp_1.py
openopt/examples/minlp_1.py
openopt/examples/miqcqp_1.py
openopt/examples/miqp_1.py
openopt/examples/mmp_1.py
openopt/examples/mmp_2.py
openopt/examples/nllsp_1.py
openopt/examples/nlp_1.py
openopt/examples/nlp_11.py
openopt/examples/nlp_2.py
openopt/examples/nlp_3.py
openopt/examples/nlp_4.py
openopt/examples/nlp_5.py
openopt/examples/nlp_ALGENCAN.py
openopt/examples/nlp_bench_1.py
openopt/examples/nlp_bench_2.py
openopt/examples/nlp_d2f.py
openopt/examples/nlsp_1.py
openopt/examples/nlsp_constrained.py
openopt/examples/nsp_1.py
openopt/examples/nssolveVSfsolve_1.py
openopt/examples/qcqp_1.py
openopt/examples/qp_1.py
openopt/examples/sdp_1.py
openopt/examples/sle_1.py
openopt/examples/snle_1.py
openopt/examples/socp_1.py
openopt/examples/stab_1.py
openopt/examples/tsp_1.py
openopt/examples/tsp_2.py
openopt/examples/tsp_3.py
openopt/examples/tsp_4.py
openopt/kernel/BPP.py
openopt/kernel/DAE.py
